{
  "generated_at": "2026-04-29T13:43:29.633740",
  "source": "IBKR via ib_insync (auto-detect port)",
  "portfolio_greeks": {
    "total_delta": -12.68,
    "total_theta": -50.96,
    "total_vega": 163.38,
    "positions_with_greeks": 28,
    "positions_without_greeks": 0
  },
  "positions": {
    "OZLN6 C7200": {
      "delta": 0.5808,
      "gamma": 0.029835,
      "theta": -0.0327,
      "vega": 0.1315,
      "iv": 0.38,
      "opt_price": 5.9155,
      "source": "black76_estimated_iv",
      "und_price": 73.66,
      "iv_used": 0.38
    },
    "SOM6 P6800": {
      "delta": -0.268,
      "gamma": 0.044926,
      "theta": -0.0252,
      "vega": 0.0858,
      "iv": 0.28,
      "opt_price": 1.2629,
      "source": "black76_estimated_iv",
      "und_price": 72.005,
      "iv_used": 0.28
    },
    "SOM6 P7200": {
      "delta": -0.4768,
      "gamma": 0.054186,
      "theta": -0.0305,
      "vega": 0.1034,
      "iv": 0.28,
      "opt_price": 2.8965,
      "source": "black76_estimated_iv",
      "und_price": 72.005,
      "iv_used": 0.28
    },
    "OZLN6 C6850": {
      "delta": 0.6856,
      "gamma": 0.026943,
      "theta": -0.0298,
      "vega": 0.1187,
      "iv": 0.38,
      "opt_price": 7.8999,
      "source": "black76_estimated_iv",
      "und_price": 73.66,
      "iv_used": 0.38
    },
    "LON6 C11700": {
      "delta": 0.3561,
      "gamma": 0.017822,
      "theta": -0.0499,
      "vega": 0.1833,
      "iv": 0.42,
      "opt_price": 4.5389,
      "source": "black76_estimated_iv",
      "und_price": 107.06,
      "iv_used": 0.42
    },
    "CON6 P2500": {
      "delta": -0.056,
      "gamma": 0.000159,
      "theta": -0.5128,
      "vega": 1.7703,
      "iv": 0.45,
      "opt_price": 18.3247,
      "source": "black76_estimated_iv",
      "und_price": 3402.0,
      "iv_used": 0.45
    },
    "LOM6 C12800": {
      "delta": 0.1356,
      "gamma": 0.013333,
      "theta": -0.0371,
      "vega": 0.0844,
      "iv": 0.42,
      "opt_price": 1.0492,
      "source": "black76_estimated_iv",
      "und_price": 107.06,
      "iv_used": 0.42
    },
    "LOM6 C12300": {
      "delta": 0.2007,
      "gamma": 0.017166,
      "theta": -0.0477,
      "vega": 0.1087,
      "iv": 0.42,
      "opt_price": 1.7066,
      "source": "black76_estimated_iv",
      "und_price": 107.06,
      "iv_used": 0.42
    },
    "OZLM6 C7300": {
      "delta": 0.5503,
      "gamma": 0.03873,
      "theta": -0.0421,
      "vega": 0.105,
      "iv": 0.38,
      "opt_price": 4.3421,
      "source": "black76_estimated_iv",
      "und_price": 73.66,
      "iv_used": 0.38
    },
    "SOM6 P6400": {
      "delta": -0.1122,
      "gamma": 0.026048,
      "theta": -0.0146,
      "vega": 0.0497,
      "iv": 0.28,
      "opt_price": 0.4162,
      "source": "black76_estimated_iv",
      "und_price": 72.005,
      "iv_used": 0.28
    },
    "OZLM6 C6700": {
      "delta": 0.771,
      "gamma": 0.029353,
      "theta": -0.0324,
      "vega": 0.0796,
      "iv": 0.38,
      "opt_price": 8.0248,
      "source": "black76_estimated_iv",
      "und_price": 73.66,
      "iv_used": 0.38
    },
    "SOM6 P6500": {
      "delta": -0.144,
      "gamma": 0.030978,
      "theta": -0.0173,
      "vega": 0.0591,
      "iv": 0.28,
      "opt_price": 0.5663,
      "source": "black76_estimated_iv",
      "und_price": 72.005,
      "iv_used": 0.28
    },
    "LON6 C9800": {
      "delta": 0.7032,
      "gamma": 0.016325,
      "theta": -0.0468,
      "vega": 0.1679,
      "iv": 0.42,
      "opt_price": 13.143,
      "source": "black76_estimated_iv",
      "und_price": 107.06,
      "iv_used": 0.42
    },
    "CON6 P2650": {
      "delta": -0.0951,
      "gamma": 0.000238,
      "theta": -0.7695,
      "vega": 2.6536,
      "iv": 0.45,
      "opt_price": 34.5352,
      "source": "black76_estimated_iv",
      "und_price": 3402.0,
      "iv_used": 0.45
    },
    "OZLN6 C7550": {
      "delta": 0.4746,
      "gamma": 0.030507,
      "theta": -0.0333,
      "vega": 0.1344,
      "iv": 0.38,
      "opt_price": 4.3113,
      "source": "black76_estimated_iv",
      "und_price": 73.66,
      "iv_used": 0.38
    },
    "LOM6 C12500": {
      "delta": 0.1724,
      "gamma": 0.015625,
      "theta": -0.0434,
      "vega": 0.0989,
      "iv": 0.42,
      "opt_price": 1.41,
      "source": "black76_estimated_iv",
      "und_price": 107.06,
      "iv_used": 0.42
    },
    "OZLM6 C7000": {
      "delta": 0.6658,
      "gamma": 0.035495,
      "theta": -0.0388,
      "vega": 0.0962,
      "iv": 0.38,
      "opt_price": 6.008,
      "source": "black76_estimated_iv",
      "und_price": 73.66,
      "iv_used": 0.38
    },
    "SOM6 P7500": {
      "delta": -0.6335,
      "gamma": 0.051024,
      "theta": -0.029,
      "vega": 0.0974,
      "iv": 0.28,
      "opt_price": 4.6834,
      "source": "black76_estimated_iv",
      "und_price": 72.005,
      "iv_used": 0.28
    },
    "CON6 P2700": {
      "delta": -0.1112,
      "gamma": 0.000267,
      "theta": -0.8621,
      "vega": 2.9716,
      "iv": 0.45,
      "opt_price": 41.7949,
      "source": "black76_estimated_iv",
      "und_price": 3402.0,
      "iv_used": 0.45
    },
    "LOM6 C12900": {
      "delta": 0.1248,
      "gamma": 0.01259,
      "theta": -0.035,
      "vega": 0.0797,
      "iv": 0.42,
      "opt_price": 0.9485,
      "source": "black76_estimated_iv",
      "und_price": 107.06,
      "iv_used": 0.42
    },
    "SOM6 P7000": {
      "delta": -0.369,
      "gamma": 0.051401,
      "theta": -0.0289,
      "vega": 0.0981,
      "iv": 0.28,
      "opt_price": 1.9716,
      "source": "black76_estimated_iv",
      "und_price": 72.005,
      "iv_used": 0.28
    },
    "CON6 P2900": {
      "delta": -0.19,
      "gamma": 0.000382,
      "theta": -1.2363,
      "vega": 4.2524,
      "iv": 0.45,
      "opt_price": 82.1276,
      "source": "black76_estimated_iv",
      "und_price": 3402.0,
      "iv_used": 0.45
    },
    "LOM6 C13000": {
      "delta": 0.1147,
      "gamma": 0.011863,
      "theta": -0.033,
      "vega": 0.0751,
      "iv": 0.42,
      "opt_price": 0.8565,
      "source": "black76_estimated_iv",
      "und_price": 107.06,
      "iv_used": 0.42
    },
    "SOM6 P7300": {
      "delta": -0.5306,
      "gamma": 0.054065,
      "theta": -0.0305,
      "vega": 0.1032,
      "iv": 0.28,
      "opt_price": 3.4404,
      "source": "black76_estimated_iv",
      "und_price": 72.005,
      "iv_used": 0.28
    },
    "LOM6 C12400": {
      "delta": 0.1861,
      "gamma": 0.016397,
      "theta": -0.0456,
      "vega": 0.1038,
      "iv": 0.42,
      "opt_price": 1.5522,
      "source": "black76_estimated_iv",
      "und_price": 107.06,
      "iv_used": 0.42
    },
    "SOM6 P6900": {
      "delta": -0.3172,
      "gamma": 0.04857,
      "theta": -0.0272,
      "vega": 0.0927,
      "iv": 0.28,
      "opt_price": 1.5909,
      "source": "black76_estimated_iv",
      "und_price": 72.005,
      "iv_used": 0.28
    },
    "OZLM6 C7100": {
      "delta": 0.6279,
      "gamma": 0.036938,
      "theta": -0.0403,
      "vega": 0.1002,
      "iv": 0.38,
      "opt_price": 5.413,
      "source": "black76_estimated_iv",
      "und_price": 73.66,
      "iv_used": 0.38
    },
    "LON6 C13300": {
      "delta": 0.1524,
      "gamma": 0.011299,
      "theta": -0.0315,
      "vega": 0.1162,
      "iv": 0.42,
      "opt_price": 1.5169,
      "source": "black76_estimated_iv",
      "und_price": 107.06,
      "iv_used": 0.42
    }
  }
}